odoo/addons/pydantic/README.rst
odoo/addons/pydantic/__init__.py
odoo/addons/pydantic/__manifest__.py
odoo/addons/pydantic/utils.py
odoo/addons/pydantic/i18n/pydantic.pot
odoo/addons/pydantic/readme/CONTRIBUTORS.rst
odoo/addons/pydantic/readme/DESCRIPTION.rst
odoo/addons/pydantic/readme/ROADMAP.rst
odoo/addons/pydantic/readme/USAGE.rst
odoo/addons/pydantic/static/description/icon.png
odoo/addons/pydantic/static/description/index.html
odoo13_addon_pydantic-13.0.1.0.1.dist-info/METADATA
odoo13_addon_pydantic-13.0.1.0.1.dist-info/WHEEL
odoo13_addon_pydantic-13.0.1.0.1.dist-info/top_level.txt
odoo13_addon_pydantic-13.0.1.0.1.dist-info/RECORD
