Metadata-Version: 2.1
Name: odoo13-addon-pydantic
Version: 13.0.1.0.1
Summary: Utility addon to ease mapping between Pydantic and Odoo models
Home-page: https://github.com/OCA/rest-framework
Author: ACSONE SA/NV,Odoo Community Association (OCA)
Author-email: support@odoo-community.org
License: LGPL-3
Platform: UNKNOWN
Classifier: Programming Language :: Python
Classifier: Framework :: Odoo
Classifier: Framework :: Odoo :: 13.0
Classifier: License :: OSI Approved :: GNU Lesser General Public License v3 (LGPLv3)
Classifier: Development Status :: 4 - Beta
Requires-Python: >=3.5
Requires-Dist: odoo (<13.1dev,>=13.0a)
Requires-Dist: pydantic
Requires-Dist: typing-extensions
Requires-Dist: contextvars ; python_version < "3.7"
